setup.py
bin/inference
bin/train
lib/__init__.py
lib/conv1d.py
lib/ensemble.py
lib/inference.py
lib/label_time_window.py
lib/lstm.py
lib/tf_idf.py
lib/train.py
lib/utils.py
parsecontent.egg-info/PKG-INFO
parsecontent.egg-info/SOURCES.txt
parsecontent.egg-info/dependency_links.txt
parsecontent.egg-info/not-zip-safe
parsecontent.egg-info/requires.txt
parsecontent.egg-info/top_level.txt