Metadata-Version: 1.0
Name: parsecontent
Version: 0.1.4
Summary: Classify social media posts
Home-page: http://github.com/dzorlu/parsecontent
Author: Deniz Zorlu
Author-email: dzorlu@gmail.com
License: MIT
Platform: UNKNOWN
